{
  "id": "293515060",
  "title": "Entorno de desarrollo Python con docker y vscode",
  "eventUrl": "https://www.meetup.com/python_malaga/events/293515060",
  "description": "En esta charla, veremos como tener nuestro entorno de desarrollo python en VScode usando Docker, veremos como crear una aplicaci\u00f3n desde cero y como probarla y depurar todos los puntos dentro del contenedor\n\nEsta charla tendr\u00e1 lugar dentro del evento opensouthcode de m\u00e1laga\nhttps://www.opensouthcode.org/conferences/opensouthcode2023",
  "shortDescription": null,
  "group": {
    "id": "33344430",
    "name": "Python M\u00e1laga"
  },
  "isNetworkEvent": false,
  "isOnline": false,
  "eventType": "PHYSICAL",
  "venue": {
    "id": "26178960",
    "name": "La T\u00e9rmica",
    "address": "Av. de los Guindos, 48",
    "city": "M\u00e1laga",
    "postalCode": "29004",
    "lng": -4.445437,
    "lat": 36.68937
  },
  "onlineVenue": null,
  "dateTime": "2023-06-09T16:30+02:00",
  "duration": "PT1H",
  "timezone": "Europe/Madrid",
  "endTime": "2023-06-09T17:30+02:00"
}